Workbook
Name Category: #REF!
Name Customer: 'Customer Info'!$A$1:$I$501
Name Customer_Head: 'Customer Info'!$A$1:$I$1
Name Product: #REF!
Name Product_Head: #REF!
Name Product_ID: #REF!
Name Product_Name: #REF!
Name Sub_Category: #REF!

Sheet Sales Order 
T1: Amount | U1: Commission %
T2: 0 | U2: 0.02
T3: 5000 | U3: 0.05
T4: 25000 | U4: 0.07
T5: 50000 | U5: 0.09
T6: 100000 | U6: 0.12
G7: By Using VLookUp Find all the First Name , Last Name and City from another Customer Info Sheet | M7: Cost* Quantity | N7: Price * Quantity | P7: Total Sales+ Shipping Cost | Q7: Total Sales- Total Cost | S7: By using above small table | T7: 250000 | U7: 0.15
S8: Calculate Commision Based on Amt
A9: Order ID | B9: Order Date | C9: Ship Date | D9: Product Category | E9: Order_Source | F9: Customer_ID | G9: Customer First Name | H9: Customer Last Name | I9: City | J9: Price | K9: Cost | L9: Quantity | M9: Total_Cost | N9: Tota_Sales | O9: Shiping Cost | P9: Tot_Sales_Amt | Q9: Profit | R9: Order Priority | S9: Sales Person Commission
A10: AU-2018-10553 | B10: 43458 | C10: 43458 | D10: Furniture | E10: Flipkart | F10: CS-04692 | G10: =VLOOKUP(F10,'Customer Info'!A2:I501,2,0) -> Cari | H10: =VLOOKUP(F10,'Customer Info'!A2:I501,3,0) -> Sayre | I10: =VLOOKUP(F10,'Customer Info'!A2:I501,5,0) -> Recklinghausen | J10: 1834 | K10: 1716 | L10: 2 | M10: =K10*L10 -> 3432 | N10: =J10*L10 -> 3668 | O10: 53 | P10: =SUM(N10,O10) -> 3721 | Q10: =N10-O10 -> 3615 | R10: Critical | S10: =VLOOKUP(P10,$T$2:U7,2,1) -> 0.02
A11: AU-2018-10651 | B11: 43304 | C11: 43306 | D11: Furniture | E11: Flipkart | F11: MG-21584 | G11: =VLOOKUP(F11,'Customer Info'!A3:I502,2,0) -> Michael | H11: =VLOOKUP(F11,'Customer Info'!A3:I502,3,0) -> Granlund | I11: =VLOOKUP(F11,'Customer Info'!A3:I502,5,0) -> Sydney | J11: 4798 | K11: 4448 | L11: 6 | M11: =K11*L11 -> 26688 | N11: =J11*L11 -> 28788 | O11: 91 | P11: =SUM(N11,O11) -> 28879 | Q11: =N11-O11 -> 28697 | R11: Medium | S11: =VLOOKUP(P11,$T$2:U8,2,1) -> 0.07
A12: AU-2018-10857 | B12: 43397 | C12: 43399 | D12: Technology | E12: Amazon | F12: ML-21811 | G12: =VLOOKUP(F12,'Customer Info'!A4:I503,2,0) -> Muhammed | H12: =VLOOKUP(F12,'Customer Info'!A4:I503,3,0) -> Lee | I12: =VLOOKUP(F12,'Customer Info'!A4:I503,5,0) -> Nellore | J12: 2808 | K12: 2674 | L12: 3 | M12: =K12*L12 -> 8022 | N12: =J12*L12 -> 8424 | O12: 47 | P12: =SUM(N12,O12) -> 8471 | Q12: =N12-O12 -> 8377 | R12: Medium | S12: =VLOOKUP(P12,$T$2:U9,2,1) -> 0.05
A13: AU-2018-10892 | B13: 43147 | C13: 43148 | D13: Furniture | E13: Flipkart | F13: RD-27712 | G13: =VLOOKUP(F13,'Customer Info'!A5:I504,2,0) -> Rick | H13: =VLOOKUP(F13,'Customer Info'!A5:I504,3,0) -> Duston | I13: =VLOOKUP(F13,'Customer Info'!A5:I504,5,0) -> Bhiwandi | J13: 1816 | K13: 1699 | L13: 2 | M13: =K13*L13 -> 3398 | N13: =J13*L13 -> 3632 | O13: 73 | P13: =SUM(N13,O13) -> 3705 | Q13: =N13-O13 -> 3559 | R13: Medium | S13: =VLOOKUP(P13,$T$2:U10,2,1) -> 0.02
A14: AU-2018-11021 | B14: 43369 | C14: 43371 | D14: Technology | E14: Snapdeal | F14: SN-28948 | G14: =VLOOKUP(F14,'Customer Info'!A6:I505,2,0) -> Steve | H14: =VLOOKUP(F14,'Customer Info'!A6:I505,3,0) -> Nguyen | I14: =VLOOKUP(F14,'Customer Info'!A6:I505,5,0) -> Delhi | J14: 1668 | K14: 1636 | L14: 4 | M14: =K14*L14 -> 6544 | N14: =J14*L14 -> 6672 | O14: 66 | P14: =SUM(N14,O14) -> 6738 | Q14: =N14-O14 -> 6606 | R14: Medium | S14: =VLOOKUP(P14,$T$2:U11,2,1) -> 0.05
A15: AU-2018-11055 | B15: 43295 | C15: 43296 | D15: Office Supplies | E15: India_Mart | F15: MM-22019 | G15: =VLOOKUP(F15,'Customer Info'!A7:I506,2,0) -> Michael | H15: =VLOOKUP(F15,'Customer Info'!A7:I506,3,0) -> Moore | I15: =VLOOKUP(F15,'Customer Info'!A7:I506,5,0) -> Melbourne | J15: 97 | K15: 92 | L15: 6 | M15: =K15*L15 -> 552 | N15: =J15*L15 -> 582 | O15: 10 | P15: =SUM(N15,O15) -> 592 | Q15: =N15-O15 -> 572 | R15: Medium | S15: =VLOOKUP(P15,$T$2:U12,2,1) -> 0.02
A16: AU-2018-11228 | B16: 43132 | C16: 43132 | D16: Furniture | E16: Amazon | F16: JO-16901 | G16: =VLOOKUP(F16,'Customer Info'!A8:I507,2,0) -> Jas | H16: =VLOOKUP(F16,'Customer Info'!A8:I507,3,0) -> O'Carroll | I16: =VLOOKUP(F16,'Customer Info'!A8:I507,5,0) -> Essen | J16: 2790 | K16: 2557 | L16: 2 | M16: =K16*L16 -> 5114 | N16: =J16*L16 -> 5580 | O16: 98 | P16: =SUM(N16,O16) -> 5678 | Q16: =N16-O16 -> 5482 | R16: Medium | S16: =VLOOKUP(P16,$T$2:U13,2,1) -> 0.05
A17: AU-2018-11473 | B17: 43256 | C17: 43258 | D17: Office Supplies | E17: Amazon | F17: CS-08000 | G17: =VLOOKUP(F17,'Customer Info'!A9:I508,2,0) -> Cindy | H17: =VLOOKUP(F17,'Customer Info'!A9:I508,3,0) -> Schnelling | I17: =VLOOKUP(F17,'Customer Info'!A9:I508,5,0) -> Balikpapan | J17: 138 | K17: 128 | L17: 3 | M17: =K17*L17 -> 384 | N17: =J17*L17 -> 414 | O17: 30 | P17: =SUM(N17,O17) -> 444 | Q17: =N17-O17 -> 384 | R17: Medium | S17: =VLOOKUP(P17,$T$2:U14,2,1) -> 0.02
A18: AU-2018-11635 | B18: 43315 | C18: 43315 | D18: Office Supplies | E18: Snapdeal | F18: JE-16318 | G18: =VLOOKUP(F18,'Customer Info'!A10:I509,2,0) -> Jeremy | H18: =VLOOKUP(F18,'Customer Info'!A10:I509,3,0) -> Ellison | I18: =VLOOKUP(F18,'Customer Info'!A10:I509,5,0) -> Jammu | J18: 162 | K18: 148 | L18: 3 | M18: =K18*L18 -> 444 | N18: =J18*L18 -> 486 | O18: 30 | P18: =SUM(N18,O18) -> 516 | Q18: =N18-O18 -> 456 | R18: Medium | S18: =VLOOKUP(P18,$T$2:U15,2,1) -> 0.02
A19: AU-2018-11675 | B19: 43262 | C19: 43264 | D19: Furniture | E19: Snapdeal | F19: CM-06731 | G19: =VLOOKUP(F19,'Customer Info'!A11:I510,2,0) -> Corinna | H19: =VLOOKUP(F19,'Customer Info'!A11:I510,3,0) -> Mitchell | I19: =VLOOKUP(F19,'Customer Info'!A11:I510,5,0) -> Augsburg | J19: 1637 | K19: 1591 | L19: 1 | M19: =K19*L19 -> 1591 | N19: =J19*L19 -> 1637 | O19: 57 | P19: =SUM(N19,O19) -> 1694 | Q19: =N19-O19 -> 1580 | R19: High | S19: =VLOOKUP(P19,$T$2:U16,2,1) -> 0.02
A20: AU-2018-11700 | B20: 43280 | C20: 43280 | D20: Furniture | E20: Snapdeal | F20: VP-33803 | G20: =VLOOKUP(F20,'Customer Info'!A12:I511,2,0) -> Victor | H20: =VLOOKUP(F20,'Customer Info'!A12:I511,3,0) -> Preis | I20: =VLOOKUP(F20,'Customer Info'!A12:I511,5,0) -> Melbourne | J20: 1364 | K20: 1274 | L20: 2 | M20: =K20*L20 -> 2548 | N20: =J20*L20 -> 2728 | O20: 56 | P20: =SUM(N20,O20) -> 2784 | Q20: =N20-O20 -> 2672 | R20: Medium | S20: =VLOOKUP(P20,$T$2:U17,2,1) -> 0.02
A21: AU-2018-11960 | B21: 43173 | C21: 43175 | D21: Office Supplies | E21: Referral | F21: JC-15796 | G21: =VLOOKUP(F21,'Customer Info'!A13:I512,2,0) -> Jenna | H21: =VLOOKUP(F21,'Customer Info'!A13:I512,3,0) -> Caffey | I21: =VLOOKUP(F21,'Customer Info'!A13:I512,5,0) -> Kanpur | J21: 169 | K21: 160 | L21: 2 | M21: =K21*L21 -> 320 | N21: =J21*L21 -> 338 | O21: 30 | P21: =SUM(N21,O21) -> 368 | Q21: =N21-O21 -> 308 | R21: Low | S21: =VLOOKUP(P21,$T$2:U18,2,1) -> 0.02
... A4815: IN-2020-99568 | B4815: 43994 | C4815: 43996 | D4815: Office Supplies | E4815: India_Mart | F4815: AO-01810 | G4815: =VLOOKUP(F4815,'Customer Info'!A4807:I5306,2,0) -> #N/A | H4815: =VLOOKUP(F4815,'Customer Info'!A4807:I5306,3,0) -> #N/A | I4815: =VLOOKUP(F4815,'Customer Info'!A4807:I5306,5,0) -> #N/A | J4815: 851 | K4815: 773 | L4815: 2 | M4815: =K4815*L4815 -> 1546 | N4815: =J4815*L4815 -> 1702 | O4815: 98 | P4815: =SUM(N4815,O4815) -> 1800 | Q4815: =N4815-O4815 -> 1604 | R4815: Critical | S4815: =VLOOKUP(P4815,$T$2:U4812,2,1) -> 0.02

Sheet Customer Info
A1: Customer ID | B1: Customer First Name | C1: Customer Last Name | D1: Segment | E1: City | F1: State | G1: Country | H1: Region | I1: Age
A2: AB-00014 | B2: Aaron | C2: Bergman | D2: Corporate | E2: Halle | F2: SaxonyAnhalt | G2: Germany | H2: Central | I2: 57
A3: AS-00460 | B3: Aaron | C3: Smayling | D3: Corporate | E3: Dresden | F3: Saxony | G3: Germany | H3: Central | I3: 61 | Q3: Enter First Name | R3: Aaron
A4: AS-00312 | B4: Aaron | C4: Smayling | D4: Home Office | E4: Port Macquarie | F4: New South Wales | G4: Australia | H4: Oceania | I4: 72 | Q4: Enter Last Name | R4: Hawkins
A5: AH-00052 | B5: Aaron | C5: Hawkins | D5: Consumer | E5: Minden | F5: North RhineWestphalia | G5: Germany | H5: Central | I5: 72 | Q5: City | R5: {=INDEX(E1:E501,MATCH(R3&R4,B1:B501&C1:C501,0))} -> Minden
A6: AB-01482 | B6: Adam | C6: Bellavance | D6: Corporate | E6: Kwinana | F6: Western Australia | G6: Australia | H6: Oceania | I6: 57
A7: AB-01343 | B7: Adam | C7: Bellavance | D7: Corporate | E7: Kaiyuan | F7: Liaoning | G7: China | H7: North Asia | I7: 79
A8: AB-01473 | B8: Adam | C8: Bellavance | D8: Consumer | E8: Medan | F8: Sumatera Utara | G8: Indonesia | H8: Southeast Asia | I8: 64
A9: AB-01525 | B9: Adrian | C9: Barton | D9: Corporate | E9: Wetzlar | F9: Hesse | G9: Germany | H9: Central | I9: 78
A10: AB-01494 | B10: Adrian | C10: Barton | D10: Consumer | E10: Zigong | F10: Sichuan | G10: China | H10: North Asia | I10: 30
A11: AS-01405 | B11: Alan | C11: Shonely | D11: Corporate | E11: Canberra | F11: Australian Capital Territory | G11: Australia | H11: Oceania | I11: 57
A12: AS-01458 | B12: Alan | C12: Schoenberger | D12: Home Office | E12: Anshan | F12: Liaoning | G12: China | H12: North Asia | I12: 40
A13: AB-02405 | B13: Alejandro | C13: Ballentine | D13: Consumer | E13: Mannheim | F13: BadenWŸrttemberg | G13: Germany | H13: Central | I13: 39
A14: AG-02487 | B14: Alejandro | C14: Grove | D14: Consumer | E14: Whyalla | F14: South Australia | G14: Australia | H14: Oceania | I14: 37
A15: AG-00272 | B15: Alex | C15: Grayson | D15: Consumer | E15: Anyang | F15: Henan | G15: China | H15: North Asia | I15: 60
A16: AA-02503 | B16: Alex | C16: Avila | D16: Consumer | E16: Agra | F16: Uttar Pradesh | G16: India | H16: Central Asia | I16: 67
A17: AA-02455 | B17: Alex | C17: Avila | D17: Consumer | E17: Berlin | F17: Berlin | G17: Germany | H17: Central | I17: 42
... A501: YS-34261 | B501: Yana | C501: Sorensen | D501: Corporate | E501: Bottrop | F501: North RhineWestphalia | G501: Germany | H501: Central | I501: 70
